codemao_diger/DBGenerator.py
codemao_diger/DBMapper/NoExistPostsMapper.py
codemao_diger/DBMapper/PostMapper.py
codemao_diger/DBMapper/__init__.py
codemao_diger/charts/board_bar/BoardEntity.py
codemao_diger/charts/board_bar/__init__.py
codemao_diger/charts/board_bar/__main__.py
codemao_diger/charts/post_bar/UserEntity.py
codemao_diger/charts/post_bar/__init__.py
codemao_diger/charts/post_bar/__main__.py
codemao_diger/charts/wordcloud/__init__.py
codemao_diger/charts/wordcloud/__main__.py
codemao_diger/requester/Requester.py
codemao_diger/requester/__init__.py
codemao_diger/requester/__main__.py
codemao_diger/requester/entity/PostEntity.py
codemao_diger/requester/entity/__init__.py
codemao_diger_rebuild-2.0.3.dist-info/METADATA
codemao_diger_rebuild-2.0.3.dist-info/WHEEL
codemao_diger_rebuild-2.0.3.dist-info/namespace_packages.txt
codemao_diger_rebuild-2.0.3.dist-info/top_level.txt
codemao_diger_rebuild-2.0.3.dist-info/zip-safe
codemao_diger_rebuild-2.0.3.dist-info/RECORD
