Metadata-Version: 2.4
Name: codemao-diger-rebuild
Version: 2.0.3
Home-page: https://github.com/Rov-Waff/codemao-diger-rebuild
Author: 
Author-email: 
Maintainer: 
Maintainer-email: 
License: MIT License
Classifier: Development Status :: 3 - Alpha
Classifier: Programming Language :: Python
Requires-Dist: bs4
Requires-Dist: jieba>=0.40
Requires-Dist: pyecharts>=2.0.0
Requires-Dist: requests>=2.32
Dynamic: classifier
Dynamic: description
Dynamic: home-page
Dynamic: keywords
Dynamic: license
Dynamic: requires-dist
